modern_python_tools/__init__.py
modern_python_tools/console.py
modern_python_tools/wikipedia.py
modern_python_tools-0.1.0.dist-info/entry_points.txt
modern_python_tools-0.1.0.dist-info/LICENSE
modern_python_tools-0.1.0.dist-info/WHEEL
modern_python_tools-0.1.0.dist-info/METADATA
modern_python_tools-0.1.0.dist-info/RECORD
